{"version":"1.5","timestamp":1607531094,"count":31,"index":{"":{"key":"","storage_key":"","template":null,"storage_timestamp":1607202585,"children":{"01.shop":1607003302,"02.o-nas":1607529455,"03.aktualnosci":1607529578,"images":1607202585,"slider":1607202585},"checksum":"dde927b23ebe2745a765253ad53691a7"},"01.shop":{"key":"shop","storage_key":"01.shop","template":"snipcart","storage_timestamp":1607530014,"markdown":{"":{"snipcart":1607530014}},"children":{"01.slubne":1607202585,"02.urodzinowe":1606331099,"03.uniwersalne":1607202585,"04.imieninowe":1607003302,"05.gratulacje":1607003302,"06.swiateczne":1607003302},"checksum":"b06df7d4fb8674484d466f1524f94e0b"},"01.shop\/01.slubne":{"key":"shop\/slubne","storage_key":"01.shop\/01.slubne","template":"snipcart_category","storage_timestamp":1607202585,"markdown":{"":{"snipcart_category":1607202585}},"children":{"kartka-sluba-1":1607003302,"kartka-sluba-2":1607202585,"kartka-sluba-3":1607202585},"checksum":"cc922ec5d886157f9ded121560d036c0"},"01.shop\/01.slubne\/kartka-sluba-1":{"key":"shop\/slubne\/kartka-sluba-1","storage_key":"01.shop\/01.slubne\/kartka-sluba-1","template":"snipcart_detail","storage_timestamp":1607003302,"markdown":{"":{"snipcart_detail":1607003302}},"checksum":"1e91f7ec6b4c13b2a9ec7eb1cea60ea7"},"01.shop\/01.slubne\/kartka-sluba-2":{"key":"shop\/slubne\/kartka-sluba-2","storage_key":"01.shop\/01.slubne\/kartka-sluba-2","template":"snipcart_detail","storage_timestamp":1607202585,"markdown":{"":{"snipcart_detail":1607202585}},"checksum":"3ccb8e3ec893c17ce5451ffcc0b0c4df"},"01.shop\/01.slubne\/kartka-sluba-3":{"key":"shop\/slubne\/kartka-sluba-3","storage_key":"01.shop\/01.slubne\/kartka-sluba-3","template":"snipcart_detail","storage_timestamp":1607202585,"markdown":{"":{"snipcart_detail":1607202585}},"checksum":"ba9f4842d642740901bf5108391fc399"},"01.shop\/02.urodzinowe":{"key":"shop\/urodzinowe","storage_key":"01.shop\/02.urodzinowe","template":"snipcart_category","storage_timestamp":1606331099,"markdown":{"":{"snipcart_category":1606330532}},"children":{"kartka-urodzinowa-1":1607202585,"kartka-urodzinowa-2":1607202585,"kartka-urodzinowa-3":1606331091,"kartka-urodzinowa-4":1607202585},"checksum":"ce6c9ff64bb3f199ff1bacd849b22c86"},"01.shop\/02.urodzinowe\/kartka-urodzinowa-1":{"key":"shop\/urodzinowe\/kartka-urodzinowa-1","storage_key":"01.shop\/02.urodzinowe\/kartka-urodzinowa-1","template":"snipcart_detail","storage_timestamp":1607202585,"markdown":{"":{"snipcart_detail":1607202585}},"checksum":"5eb423cbdc98a609364d622eadb9d96f"},"01.shop\/02.urodzinowe\/kartka-urodzinowa-2":{"key":"shop\/urodzinowe\/kartka-urodzinowa-2","storage_key":"01.shop\/02.urodzinowe\/kartka-urodzinowa-2","template":"snipcart_detail","storage_timestamp":1607202585,"markdown":{"":{"snipcart_detail":1607202585}},"checksum":"510fc67f46a5d1f2846222880b8bd29c"},"01.shop\/02.urodzinowe\/kartka-urodzinowa-3":{"key":"shop\/urodzinowe\/kartka-urodzinowa-3","storage_key":"01.shop\/02.urodzinowe\/kartka-urodzinowa-3","template":"snipcart_detail","storage_timestamp":1606331091,"markdown":{"":{"snipcart_detail":1606330777}},"checksum":"1a4b6cf4a10b3bf3e237370a7ff55756"},"01.shop\/02.urodzinowe\/kartka-urodzinowa-4":{"key":"shop\/urodzinowe\/kartka-urodzinowa-4","storage_key":"01.shop\/02.urodzinowe\/kartka-urodzinowa-4","template":"snipcart_detail","storage_timestamp":1607202585,"markdown":{"":{"snipcart_detail":1607202585}},"checksum":"f602feea305841f4578852a9ee61042e"},"01.shop\/03.uniwersalne":{"key":"shop\/uniwersalne","storage_key":"01.shop\/03.uniwersalne","template":"snipcart_category","storage_timestamp":1607202585,"markdown":{"":{"snipcart_category":1607202585}},"children":{"kartka-uniwersalna-1":1607003302,"kartka-uniwersalna-2":1607003302,"kartka-uniwersalna-3":1607003302},"checksum":"9e54f51f859e57e65e3e02aa7f34bca9"},"01.shop\/03.uniwersalne\/kartka-uniwersalna-1":{"key":"shop\/uniwersalne\/kartka-uniwersalna-1","storage_key":"01.shop\/03.uniwersalne\/kartka-uniwersalna-1","template":"snipcart_detail","storage_timestamp":1607003302,"markdown":{"":{"snipcart_detail":1607003302}},"checksum":"49220e31602c984434a5fa103921b53b"},"01.shop\/03.uniwersalne\/kartka-uniwersalna-2":{"key":"shop\/uniwersalne\/kartka-uniwersalna-2","storage_key":"01.shop\/03.uniwersalne\/kartka-uniwersalna-2","template":"snipcart_detail","storage_timestamp":1607003302,"markdown":{"":{"snipcart_detail":1607003302}},"checksum":"803b3ef8f815d9ce06c8b6717aea4289"},"01.shop\/03.uniwersalne\/kartka-uniwersalna-3":{"key":"shop\/uniwersalne\/kartka-uniwersalna-3","storage_key":"01.shop\/03.uniwersalne\/kartka-uniwersalna-3","template":"snipcart_detail","storage_timestamp":1607003302,"markdown":{"":{"snipcart_detail":1607003302}},"checksum":"1766f7fe43ecc8a1b2772c60af7254e1"},"01.shop\/04.imieninowe":{"key":"shop\/imieninowe","storage_key":"01.shop\/04.imieninowe","template":"snipcart_category","storage_timestamp":1607003302,"markdown":{"":{"snipcart_category":1607003302}},"children":{"kartka-imieninowa-1":1607003302,"kartka-imieninowa-2":1607003302,"kartka-imieninowa-3":1607003302},"checksum":"c20ce6c588e91f3daabecc0b5a57e046"},"01.shop\/04.imieninowe\/kartka-imieninowa-1":{"key":"shop\/imieninowe\/kartka-imieninowa-1","storage_key":"01.shop\/04.imieninowe\/kartka-imieninowa-1","template":"snipcart_detail","storage_timestamp":1607003302,"markdown":{"":{"snipcart_detail":1607003302}},"checksum":"4bf88083cd1e45b39a4fbcb96400cf2a"},"01.shop\/04.imieninowe\/kartka-imieninowa-2":{"key":"shop\/imieninowe\/kartka-imieninowa-2","storage_key":"01.shop\/04.imieninowe\/kartka-imieninowa-2","template":"snipcart_detail","storage_timestamp":1607003302,"markdown":{"":{"snipcart_detail":1607003302}},"checksum":"02eccf46564bdb265f08885fd057d55f"},"01.shop\/04.imieninowe\/kartka-imieninowa-3":{"key":"shop\/imieninowe\/kartka-imieninowa-3","storage_key":"01.shop\/04.imieninowe\/kartka-imieninowa-3","template":"snipcart_detail","storage_timestamp":1607003302,"markdown":{"":{"snipcart_detail":1607003302}},"checksum":"534b5d37055df72af38bb97590b3145e"},"01.shop\/05.gratulacje":{"key":"shop\/gratulacje","storage_key":"01.shop\/05.gratulacje","template":"snipcart_category","storage_timestamp":1607003302,"markdown":{"":{"snipcart_category":1607003302}},"children":{"kartka-gratulacje-1":1607528735,"kartka-gratulacje-2":1607003302,"kartka-gratulacje-3":1607003302},"checksum":"a351ac673da421bdc0ab44c656cfa574"},"01.shop\/05.gratulacje\/kartka-gratulacje-1":{"key":"shop\/gratulacje\/kartka-gratulacje-1","storage_key":"01.shop\/05.gratulacje\/kartka-gratulacje-1","template":"snipcart_detail","storage_timestamp":1607528735,"markdown":{"":{"snipcart_detail":1607528735}},"checksum":"8db9287dbef0d4d2ba51f917203b3cfa"},"01.shop\/05.gratulacje\/kartka-gratulacje-2":{"key":"shop\/gratulacje\/kartka-gratulacje-2","storage_key":"01.shop\/05.gratulacje\/kartka-gratulacje-2","template":"snipcart_detail","storage_timestamp":1607003302,"markdown":{"":{"snipcart_detail":1607003302}},"checksum":"b98430e6004ea0dcb49e2ccac177faa7"},"01.shop\/05.gratulacje\/kartka-gratulacje-3":{"key":"shop\/gratulacje\/kartka-gratulacje-3","storage_key":"01.shop\/05.gratulacje\/kartka-gratulacje-3","template":"snipcart_detail","storage_timestamp":1607003302,"markdown":{"":{"snipcart_detail":1607003302}},"checksum":"e88027f241cb44d2b06de50c324d3874"},"01.shop\/06.swiateczne":{"key":"shop\/swiateczne","storage_key":"01.shop\/06.swiateczne","template":"snipcart_category","storage_timestamp":1607003302,"markdown":{"":{"snipcart_category":1607003302}},"children":{"kartka-swiateczna-1":1607003302,"kartka-swiateczna-2":1607003302,"kartka-swiateczna-3":1607003302},"checksum":"b8e138bfbbd912d5ec875ee0a8710cee"},"01.shop\/06.swiateczne\/kartka-swiateczna-1":{"key":"shop\/swiateczne\/kartka-swiateczna-1","storage_key":"01.shop\/06.swiateczne\/kartka-swiateczna-1","template":"snipcart_detail","storage_timestamp":1607003302,"markdown":{"":{"snipcart_detail":1607003302}},"checksum":"7b5151fa7cfc4d00101b2ddff63abf8f"},"01.shop\/06.swiateczne\/kartka-swiateczna-2":{"key":"shop\/swiateczne\/kartka-swiateczna-2","storage_key":"01.shop\/06.swiateczne\/kartka-swiateczna-2","template":"snipcart_detail","storage_timestamp":1607003302,"markdown":{"":{"snipcart_detail":1607003302}},"checksum":"c2fab6b43945bfd68604d82948d40727"},"01.shop\/06.swiateczne\/kartka-swiateczna-3":{"key":"shop\/swiateczne\/kartka-swiateczna-3","storage_key":"01.shop\/06.swiateczne\/kartka-swiateczna-3","template":"snipcart_detail","storage_timestamp":1607003302,"markdown":{"":{"snipcart_detail":1607003302}},"checksum":"a0768052e9fb29c2c81e00f1ead568bd"},"02.o-nas":{"key":"o-nas","storage_key":"02.o-nas","template":"snipcart","storage_timestamp":1607530187,"markdown":{"":{"snipcart":1607530187}},"checksum":"4642e667585f20d152eb8d50e7aeae8b"},"03.aktualnosci":{"key":"aktualnosci","storage_key":"03.aktualnosci","template":"snipcart","storage_timestamp":1607531082,"markdown":{"":{"snipcart":1607531082}},"checksum":"e40e70ded2a701f43963db81f165286e"},"images":{"key":"images","storage_key":"images","template":null,"storage_timestamp":1607202585,"checksum":"4a1fdac7e3a900dcb80e3ab37fc74940"},"slider":{"key":"slider","storage_key":"slider","template":"blog","storage_timestamp":1607530985,"markdown":{"":{"blog":1607530985,"lightslider":1606322662}},"checksum":"2ef16b1e97fde8d8e46277c001b7dab5"}}}